pylibsdm/__init__.py
pylibsdm/backend/__init__.py
pylibsdm/backend/validate.py
pylibsdm/cli/__init__.py
pylibsdm/cli/provision.py
pylibsdm/cli/tap.py
pylibsdm/tag/__init__.py
pylibsdm/tag/ntag424dna/__init__.py
pylibsdm/tag/ntag424dna/const.py
pylibsdm/tag/ntag424dna/structs.py
pylibsdm/tag/ntag424dna/tag.py
pylibsdm/tag/tag.py
pylibsdm/util.py
pylibsdm-1.0.0a0.dev2.dist-info/LICENSE
pylibsdm-1.0.0a0.dev2.dist-info/LICENSES/LGPL-2.0-or-later.txt
pylibsdm-1.0.0a0.dev2.dist-info/METADATA
pylibsdm-1.0.0a0.dev2.dist-info/WHEEL
pylibsdm-1.0.0a0.dev2.dist-info/entry_points.txt
pylibsdm-1.0.0a0.dev2.dist-info/RECORD
