Metadata-Version: 2.1
Name: pylibsdm
Version: 1.0.0a0.dev2
Summary: Python library for handling Secure Dynamic Messaging (SDM) of NFC cards like the NTAG 424 DNA
Home-page: https://codeberg.org/Bergblau/pylibsdm
License: Apache-2.0
Keywords: nfc,ntag424
Author: Dominik George
Author-email: nik@naturalnet.de
Requires-Python: >=3.9,<4.0
Classifier: Development Status :: 3 - Alpha
Classifier: Environment :: Console
Classifier: Environment :: Web Environment
Classifier: Intended Audience :: Developers
Classifier: Intended Audience :: Information Technology
Classifier: License :: OSI Approved :: Apache Software License
Classifier: Programming Language :: Python :: 3
Classifier: Programming Language :: Python :: 3.9
Classifier: Programming Language :: Python :: 3.10
Classifier: Programming Language :: Python :: 3.11
Classifier: Topic :: Security :: Cryptography
Classifier: Topic :: Software Development :: Libraries
Classifier: Topic :: Utilities
Provides-Extra: cli
Requires-Dist: nfcpy (>=1.0.4,<2.0.0)
Requires-Dist: pycryptodome (>=3.18.0,<4.0.0)
Requires-Dist: pydantic (>=1.9,<3.0)
Requires-Dist: typer[all] (>=0.9.0,<0.10.0) ; extra == "cli"
Project-URL: Repository, https://codeberg.org/Bergblau/pylibsdm
